synteles_platform_mcp/__init__.py
synteles_platform_mcp/__main__.py
synteles_platform_mcp/models.py
synteles_platform_mcp/server.py
synteles_platform_mcp/auth/__init__.py
synteles_platform_mcp/auth/oauth_client.py
synteles_platform_mcp/auth/token_store.py
synteles_platform_mcp-0.1.5.dist-info/METADATA
synteles_platform_mcp-0.1.5.dist-info/WHEEL
synteles_platform_mcp-0.1.5.dist-info/entry_points.txt
synteles_platform_mcp-0.1.5.dist-info/RECORD
